{
    "features": [
        {
            "feature_type": "building",
            "geometry": null,
            "id": "4B8302DA-21AD-401F-AF45-1DFD956B80B5",
            "properties": {
                "address_id": "6948DF80-14BD-4E04-8842-7668D9C001F5",
                "alt_name": null,
                "category": "unspecified",
                "display_point": {
                    "coordinates": [
                        -3.689318,
                        40.399415
                        
                    ],
                    "type": "Point"
                },
                "name": {
                    "en": "AWS Madrid"
                },
                "restriction": null
            },
            "type": "Feature"
        }
    ],
    "name": "building",
    "type": "FeatureCollection"
}
